{"openapi":"3.0.1","info":{"title":"Trading Api","version":"1.0"},"paths":{"/api/internal-admin/v1/crypto-configuration/crypto-currency-price/{tradingPair}":{"put":{"tags":["CryptoConfiguration"],"summary":"Update crypto currency price (Auth policies: InternalAdmin)","parameters":[{"name":"tradingPair","in":"path","description":"Trading pair","required":true,"schema":{"minLength":1,"type":"string","description":"Trading pair"}}],"requestBody":{"description":"Currency","content":{"application/json":{"schema":{"$ref":"#/components/schemas/CryptoCurrencyPriceRequestModel"}},"text/json":{"schema":{"$ref":"#/components/schemas/CryptoCurrencyPriceRequestModel"}},"application/*+json":{"schema":{"$ref":"#/components/schemas/CryptoCurrencyPriceRequestModel"}}}},"responses":{"200":{"description":"Success","content":{"application/json":{"schema":{"$ref":"#/components/schemas/CryptoCurrencyPriceRequestModel"}}}},"401":{"description":"Unauthorized","content":{"application/json":{"schema":{"$ref":"#/components/schemas/ProblemDetails"}}}},"403":{"description":"Forbidden","content":{"application/json":{"schema":{"$ref":"#/components/schemas/ProblemDetails"}}}}},"security":[{"Bearer":["InternalAdmin"]}]}},"/api/internal-admin/v1/crypto-configuration/crypto-currency-discretion":{"post":{"tags":["CryptoConfiguration"],"summary":"Set up asset discretion (Auth policies: InternalAdmin)","requestBody":{"description":"Currency with discretion","content":{"application/json":{"schema":{"$ref":"#/components/schemas/CryptoCurrencyDiscretionModel"}},"text/json":{"schema":{"$ref":"#/components/schemas/CryptoCurrencyDiscretionModel"}},"application/*+json":{"schema":{"$ref":"#/components/schemas/CryptoCurrencyDiscretionModel"}}}},"responses":{"200":{"description":"Success","content":{"application/json":{"schema":{"$ref":"#/components/schemas/CryptoCurrencyDiscretionModel"}}}},"401":{"description":"Unauthorized","content":{"application/json":{"schema":{"$ref":"#/components/schemas/ProblemDetails"}}}},"403":{"description":"Forbidden","content":{"application/json":{"schema":{"$ref":"#/components/schemas/ProblemDetails"}}}}},"security":[{"Bearer":["InternalAdmin"]}]},"get":{"tags":["CryptoConfiguration"],"summary":"Retrieve assets discretion list (Auth policies: InternalAdmin)","parameters":[{"name":"SortingAscending","in":"query","description":"Whether to sort in ascending order","schema":{"type":"boolean"}}],"responses":{"200":{"description":"Success","content":{"application/json":{"schema":{"type":"array","items":{"$ref":"#/components/schemas/CryptoCurrencyDiscretionModel"}}}}},"401":{"description":"Unauthorized","content":{"application/json":{"schema":{"$ref":"#/components/schemas/ProblemDetails"}}}},"403":{"description":"Forbidden","content":{"application/json":{"schema":{"$ref":"#/components/schemas/ProblemDetails"}}}}},"security":[{"Bearer":["InternalAdmin"]}]}},"/api/trust/v1/crypto-currency/crypto-currency-price/{network}/{currency}":{"get":{"tags":["CryptoCurrency"],"summary":"Get crypto currency price (Auth)","parameters":[{"name":"network","in":"path","description":"Network","required":true,"schema":{"$ref":"#/components/schemas/Network"}},{"name":"currency","in":"path","description":"Currency","required":true,"schema":{"$ref":"#/components/schemas/CryptoCurrency"}},{"name":"SpreadBasisPoints","in":"query","description":"Spread BasisPoints","schema":{"type":"number","description":"Spread BasisPoints","format":"double","nullable":true}}],"responses":{"200":{"description":"Success","content":{"application/json":{"schema":{"$ref":"#/components/schemas/CryptoCurrencyPriceResponseModel"}}}},"401":{"description":"Unauthorized","content":{"application/json":{"schema":{"$ref":"#/components/schemas/ProblemDetails"}}}},"403":{"description":"Forbidden","content":{"application/json":{"schema":{"$ref":"#/components/schemas/ProblemDetails"}}}}},"security":[{"Bearer":[]}]}},"/api/trust/v1/crypto-currency/crypto-currency-price/list":{"get":{"tags":["CryptoCurrency"],"summary":"Get crypto currency prices list (Auth)","parameters":[{"name":"filter","in":"query","description":"Coins filter represented by string pairs of kind cryptoCurrency-network","schema":{"type":"array","items":{"type":"string"}}}],"responses":{"200":{"description":"Success","content":{"application/json":{"schema":{"$ref":"#/components/schemas/CryptoCurrencyPriceListItemResponseModelCollectionResponseModel"}}}},"400":{"description":"Bad Request","content":{"application/json":{"schema":{"$ref":"#/components/schemas/ProblemDetails"}}}},"401":{"description":"Unauthorized","content":{"application/json":{"schema":{"$ref":"#/components/schemas/ProblemDetails"}}}},"403":{"description":"Forbidden","content":{"application/json":{"schema":{"$ref":"#/components/schemas/ProblemDetails"}}}}},"security":[{"Bearer":[]}]}},"/api/internal-admin/v1/talos-order-status-check-trigger/{orderId}":{"post":{"tags":["InternalAdmin"],"summary":" (Auth policies: InternalAdmin)","parameters":[{"name":"orderId","in":"path","required":true,"schema":{"type":"string","format":"uuid"}}],"responses":{"202":{"description":"Accepted"},"401":{"description":"Unauthorized","content":{"application/json":{"schema":{"$ref":"#/components/schemas/ProblemDetails"}}}},"403":{"description":"Forbidden"}},"security":[{"Bearer":["InternalAdmin"]}]}},"/api/ops/v1/liquidity-provider-order-refunds":{"get":{"tags":["LiquidityProviderOrderRefunds"],"summary":"Retrieves a .csv file with partially filled order refunds based on certain filters. (Auth policies: Ops)","parameters":[{"name":"OrganizationId","in":"query","description":"Organization Identifier","schema":{"type":"string","description":"Organization Identifier","format":"uuid","nullable":true}},{"name":"Status","in":"query","description":"Status to filter by","schema":{"$ref":"#/components/schemas/PartiallyFilledOrderStatus"}},{"name":"FromDate","in":"query","description":"Date from","schema":{"type":"string","description":"Date from","format":"date-time","nullable":true}},{"name":"ToDate","in":"query","description":"Date to","schema":{"type":"string","description":"Date to","format":"date-time","nullable":true}}],"responses":{"200":{"description":"Success","content":{"application/json":{"schema":{"type":"string","format":"binary"}}}},"401":{"description":"Unauthorized","content":{"application/json":{"schema":{"$ref":"#/components/schemas/ProblemDetails"}}}},"403":{"description":"Forbidden"},"404":{"description":"Not Found","content":{"application/json":{"schema":{"$ref":"#/components/schemas/ProblemDetails"}}}}},"security":[{"Bearer":["Ops"]}]}},"/api/internal-admin/v1/liquidity-providers/default/sandbox/talos-trading-pair":{"post":{"tags":["LiquidityProviders"],"summary":"Add custom trading pairs for testing purposes.\r\nWorks on sandbox environments only (int, stage, dev, sandbox, local) (Auth policies: InternalAdmin)","parameters":[{"name":"Idempotency-Key","in":"header","description":"The idempotency key for the endpoint","schema":{"type":"string","format":"uuid"}}],"requestBody":{"description":"Trading pair data model","content":{"application/json":{"schema":{"$ref":"#/components/schemas/TradingPairDataModel"}},"text/json":{"schema":{"$ref":"#/components/schemas/TradingPairDataModel"}},"application/*+json":{"schema":{"$ref":"#/components/schemas/TradingPairDataModel"}}}},"responses":{"200":{"description":"Success","content":{"application/json":{"schema":{"$ref":"#/components/schemas/TradingPairDataModel"}}}},"400":{"description":"Bad Request","content":{"application/json":{"schema":{"$ref":"#/components/schemas/ProblemDetails"}}}},"401":{"description":"Unauthorized"},"403":{"description":"Forbidden"}},"security":[{"Bearer":["InternalAdmin"]}]}},"/api/ops/v1/talos-order-configuration/{orgId}":{"get":{"tags":["Ops"],"summary":" (Auth policies: Ops)","parameters":[{"name":"orgId","in":"path","required":true,"schema":{"type":"string","format":"uuid"}}],"responses":{"200":{"description":"Success","content":{"application/json":{"schema":{"$ref":"#/components/schemas/TalosOrderConfigurationResponse"}}}},"401":{"description":"Unauthorized","content":{"application/json":{"schema":{"$ref":"#/components/schemas/ProblemDetails"}}}},"403":{"description":"Forbidden"}},"security":[{"Bearer":["Ops"]}]}},"/api/ops/v1/talos-order-configuration":{"get":{"tags":["Ops"],"summary":" (Auth policies: Ops)","responses":{"200":{"description":"Success","content":{"application/json":{"schema":{"$ref":"#/components/schemas/TalosOrderConfigurationsResponse"}}}},"401":{"description":"Unauthorized","content":{"application/json":{"schema":{"$ref":"#/components/schemas/ProblemDetails"}}}},"403":{"description":"Forbidden"}},"security":[{"Bearer":["Ops"]}]},"put":{"tags":["Ops"],"summary":" (Auth policies: Ops)","requestBody":{"content":{"application/json":{"schema":{"$ref":"#/components/schemas/UpdateTalosOrderConfigurationRequest"}},"text/json":{"schema":{"$ref":"#/components/schemas/UpdateTalosOrderConfigurationRequest"}},"application/*+json":{"schema":{"$ref":"#/components/schemas/UpdateTalosOrderConfigurationRequest"}}}},"responses":{"200":{"description":"Success"},"401":{"description":"Unauthorized","content":{"application/json":{"schema":{"$ref":"#/components/schemas/ProblemDetails"}}}},"403":{"description":"Forbidden"}},"security":[{"Bearer":["Ops"]}]},"post":{"tags":["Ops"],"summary":" (Auth policies: Ops)","requestBody":{"content":{"application/json":{"schema":{"$ref":"#/components/schemas/CreateTalosOrderConfigurationRequest"}},"text/json":{"schema":{"$ref":"#/components/schemas/CreateTalosOrderConfigurationRequest"}},"application/*+json":{"schema":{"$ref":"#/components/schemas/CreateTalosOrderConfigurationRequest"}}}},"responses":{"200":{"description":"Success"},"401":{"description":"Unauthorized","content":{"application/json":{"schema":{"$ref":"#/components/schemas/ProblemDetails"}}}},"403":{"description":"Forbidden"}},"security":[{"Bearer":["Ops"]}]}},"/api/ops/v1/otc/trades/initiate":{"post":{"tags":["Ops"],"summary":"OTC Buy/Sell crypto. (Auth policies: Ops)","parameters":[{"name":"Idempotency-Key","in":"header","description":"The idempotency key for the endpoint","schema":{"type":"string","format":"uuid"}}],"requestBody":{"description":"Buy/sell crypto request model","content":{"application/json":{"schema":{"$ref":"#/components/schemas/OtcTradeRequestModel"}},"text/json":{"schema":{"$ref":"#/components/schemas/OtcTradeRequestModel"}},"application/*+json":{"schema":{"$ref":"#/components/schemas/OtcTradeRequestModel"}}}},"responses":{"201":{"description":"Created","content":{"application/json":{"schema":{"$ref":"#/components/schemas/TradeResponseModel"}}}},"400":{"description":"Bad Request","content":{"application/json":{"schema":{"$ref":"#/components/schemas/ProblemDetails"}}}},"401":{"description":"Unauthorized","content":{"application/json":{"schema":{"$ref":"#/components/schemas/ProblemDetails"}}}},"403":{"description":"Forbidden"},"404":{"description":"Not Found","content":{"application/json":{"schema":{"$ref":"#/components/schemas/ProblemDetails"}}}}},"security":[{"Bearer":["Ops"]}]}},"/api/ops/v1/otc/trades/{paymentId}":{"patch":{"tags":["Ops"],"summary":"To complete or abort UTC trade (Auth policies: Ops)","parameters":[{"name":"paymentId","in":"path","description":"Payment Id","required":true,"schema":{"type":"string","format":"uuid"}}],"requestBody":{"description":"The update trade request","content":{"application/json":{"schema":{"$ref":"#/components/schemas/UpdateOtcTradeRequestModel"}},"text/json":{"schema":{"$ref":"#/components/schemas/UpdateOtcTradeRequestModel"}},"application/*+json":{"schema":{"$ref":"#/components/schemas/UpdateOtcTradeRequestModel"}}}},"responses":{"204":{"description":"No Content"},"400":{"description":"Bad Request","content":{"application/json":{"schema":{"$ref":"#/components/schemas/ProblemDetails"}}}},"401":{"description":"Unauthorized","content":{"application/json":{"schema":{"$ref":"#/components/schemas/ProblemDetails"}}}},"403":{"description":"Forbidden"},"404":{"description":"Not Found","content":{"application/json":{"schema":{"$ref":"#/components/schemas/ProblemDetails"}}}}},"security":[{"Bearer":["Ops"]}]}},"/api/ops/v1/otc/trades":{"get":{"tags":["Ops"],"summary":"Get OTC trades (Auth policies: Ops)","parameters":[{"name":"Page","in":"query","description":"Page count","schema":{"type":"integer","format":"int32"}},{"name":"PageSize","in":"query","description":"PageSize","schema":{"type":"integer","format":"int32"}}],"responses":{"200":{"description":"Success","content":{"application/json":{"schema":{"$ref":"#/components/schemas/OtcTradeResponseModelPageResponseModel"}}}},"400":{"description":"Bad Request","content":{"application/json":{"schema":{"$ref":"#/components/schemas/ProblemDetails"}}}},"401":{"description":"Unauthorized","content":{"application/json":{"schema":{"$ref":"#/components/schemas/ProblemDetails"}}}},"403":{"description":"Forbidden"}},"security":[{"Bearer":["Ops"]}]}},"/api/trust/v1/partially-filled-order-refunds/liquidity-provider-order-refunds":{"get":{"tags":["PartiallyFilledOrderRefunds"],"summary":"Retrieves a .csv file with partially filled order refunds based on certain filters. (Auth)","parameters":[{"name":"Status","in":"query","description":"Status to filter by","schema":{"$ref":"#/components/schemas/PartiallyFilledOrderStatus"}},{"name":"FromDate","in":"query","description":"Date from","schema":{"type":"string","description":"Date from","format":"date-time","nullable":true}},{"name":"ToDate","in":"query","description":"Date to","schema":{"type":"string","description":"Date to","format":"date-time","nullable":true}}],"responses":{"200":{"description":"Success","content":{"application/json":{"schema":{"type":"string","format":"binary"}}}},"401":{"description":"Unauthorized","content":{"application/json":{"schema":{"$ref":"#/components/schemas/ProblemDetails"}}}},"403":{"description":"Forbidden"},"404":{"description":"Not Found","content":{"application/json":{"schema":{"$ref":"#/components/schemas/ProblemDetails"}}}}},"security":[{"Bearer":[]}]}},"/api/trust/v1/precious-metals/price/{type}":{"get":{"tags":["PreciousMetals"],"summary":"Get precious metals price (Auth)","parameters":[{"name":"type","in":"path","description":"Type of a precious metal","required":true,"schema":{"$ref":"#/components/schemas/PreciousMetalType"}},{"name":"SpreadBasisPoints","in":"query","description":"Integrator spread basis points","schema":{"type":"number","description":"Integrator spread basis points","format":"double","nullable":true}},{"name":"SpreadFiatPerUnit","in":"query","description":"Integrator spread fiat per unit","schema":{"type":"number","description":"Integrator spread fiat per unit","format":"double","nullable":true}}],"responses":{"200":{"description":"Success","content":{"application/json":{"schema":{"$ref":"#/components/schemas/PreciousMetalPriceResponseModel"}}}},"400":{"description":"Bad Request","content":{"application/json":{"schema":{"$ref":"#/components/schemas/ProblemDetails"}}}},"401":{"description":"Unauthorized","content":{"application/json":{"schema":{"$ref":"#/components/schemas/ProblemDetails"}}}},"403":{"description":"Forbidden"}},"security":[{"Bearer":[]}]}},"/api/trust/v1/trades":{"post":{"tags":["Trades"],"summary":"Buy/Sell crypto. (Auth)","parameters":[{"name":"Idempotency-Key","in":"header","description":"The idempotency key for the endpoint","schema":{"type":"string","format":"uuid"}}],"requestBody":{"description":"Buy/sell crypto request model","content":{"application/json":{"schema":{"$ref":"#/components/schemas/TradeRequestModel"}},"text/json":{"schema":{"$ref":"#/components/schemas/TradeRequestModel"}},"application/*+json":{"schema":{"$ref":"#/components/schemas/TradeRequestModel"}}}},"responses":{"201":{"description":"Buy/sell crypto process started successfully","content":{"application/json":{"schema":{"$ref":"#/components/schemas/TradeResponseModel"}}}},"400":{"description":"Bad request model data","content":{"application/json":{"schema":{"$ref":"#/components/schemas/ProblemDetails"}}}},"401":{"description":"Unauthorized","content":{"application/json":{"schema":{"$ref":"#/components/schemas/ProblemDetails"}}}},"403":{"description":"Forbidden"},"404":{"description":"Custodial account was not found","content":{"application/json":{"schema":{"$ref":"#/components/schemas/ProblemDetails"}}}}},"security":[{"Bearer":[]}]}}},"components":{"schemas":{"AssetData":{"type":"object","properties":{"asset":{"$ref":"#/components/schemas/ModelAssetFiatType"},"network":{"$ref":"#/components/schemas/ModelNetworkChain"}},"additionalProperties":false,"description":"Asset data"},"AssetDataFrom":{"type":"object","properties":{"asset":{"$ref":"#/components/schemas/ModelAssetFiatType"},"network":{"$ref":"#/components/schemas/ModelNetworkChain"},"amount":{"type":"number","description":"Gets amount.","format":"double","nullable":true}},"additionalProperties":false,"description":"Asset data from"},"CreateTalosOrderConfigurationRequest":{"type":"object","properties":{"organizationId":{"type":"string","format":"uuid"},"timeInForce":{"$ref":"#/components/schemas/TimeInForce"}},"additionalProperties":false},"CryptoCurrency":{"enum":["eth","matic","btc","usdc","sol","ada","xlm","dot","link","algo","busd","bnb","avax","ltc","uni","crv","aave","eos","bch","xtz","comp","bat","shib","doge","grt","sushi","sand","enj","axs","mana","mkr","yfi","atom","ape","dai","usdt","near","trx","ftm","xrp","flrns","flow","qnt","hbar","chz","gala","smtf","pol"],"type":"string","description":"Types of the crypto currency"},"CryptoCurrencyDiscretionModel":{"required":["cryptoCurrency","discretion"],"type":"object","properties":{"cryptoCurrency":{"$ref":"#/components/schemas/CryptoCurrency"},"discretion":{"maximum":10000,"minimum":0,"type":"integer","format":"int32"}},"additionalProperties":false},"CryptoCurrencyPriceListItemResponseModel":{"type":"object","properties":{"network":{"$ref":"#/components/schemas/Network"},"currency":{"$ref":"#/components/schemas/CryptoCurrency"},"price":{"$ref":"#/components/schemas/Price"}},"additionalProperties":false},"CryptoCurrencyPriceListItemResponseModelCollectionResponseModel":{"type":"object","properties":{"data":{"type":"array","items":{"$ref":"#/components/schemas/CryptoCurrencyPriceListItemResponseModel"},"nullable":true}},"additionalProperties":false},"CryptoCurrencyPriceRequestFilterExternal":{"type":"object","properties":{"spreadBasisPoints":{"type":"number","description":"Spread BasisPoints","format":"double","nullable":true}},"additionalProperties":false,"description":"Crypto currency price request filter external"},"CryptoCurrencyPriceRequestModel":{"required":["buyPrice","sellPrice"],"type":"object","properties":{"buyPrice":{"minimum":0,"exclusiveMinimum":true,"type":"number","description":"Buy price","format":"double"},"sellPrice":{"minimum":0,"exclusiveMinimum":true,"type":"number","description":"Sell price","format":"double"}},"additionalProperties":false,"description":"Crypto currency price request"},"CryptoCurrencyPriceResponseModel":{"type":"object","properties":{"price":{"$ref":"#/components/schemas/Price"}},"additionalProperties":false,"description":"Crypto currency price response"},"FundsStorageResponseModel":{"type":"object","properties":{"identityId":{"type":"string","description":"Identity identifier","format":"uuid","nullable":true},"custodialAccountId":{"type":"string","description":"Custodial account identifier","format":"uuid","nullable":true}},"additionalProperties":false,"description":"Funds storage response model"},"InternalAdminRefundsDataRequestModel":{"type":"object","properties":{"status":{"$ref":"#/components/schemas/PartiallyFilledOrderStatus"},"fromDate":{"type":"string","description":"Date from","format":"date-time","nullable":true},"toDate":{"type":"string","description":"Date to","format":"date-time","nullable":true},"organizationId":{"type":"string","description":"Organization Identifier","format":"uuid","nullable":true}},"additionalProperties":false},"ModelAssetFiatType":{"enum":["usd","btc","eth","matic","usdc","sol","ada","xlm","dot","link","algo","bnb","busd","avax","ltc","uni","crv","aave","eos","bch","xtz","comp","bat","shib","doge","grt","sushi","sand","enj","axs","mana","mkr","yfi","atom","ape","dai","usdt","near","trx","ftm","xrp","flrns","flow","qnt","hbar","chz","gala","smtf","pol","gold","silver"],"type":"string","description":"Asset fiat type"},"ModelNetworkChain":{"enum":["mainnet","bnbSmartChainMainnet","eosMainnet","bnbSmartChainTestnet","polygonMainnet","fantomMainnet","eosTestnet","bitcoinMainnet","cosmosHub","cosmosHubTestnet","bitcoinTestnet","bchMainnet","bchTestnet","solanaMainnet","solanaDevnet","polkadotMainnet","polkadotWestend","cardanoMainnet","cardanoTestnet","algorandMainnet","algorandTestnet","stellarMainnet","stellarTestnet","litecoinMainnet","litecoinTestnet","tezosMainnet","tezosTestnet","arbitrumMainnet","avalancheFuji","avalancheMainnet","polygonMumbai","polygonAmoy","rippleMainnet","rippleTestnet","arbitrumSepolia","dogeTestnet","dogeMainnet","nearMainnet","nearTestnet","tronMainnet","tronTestnet","flowMainnet","flowTestnet","hederaMainnet","hederaTestnet","sepolia"],"type":"string","description":"Supported networks"},"ModelOrderType":{"enum":["market","limit"],"type":"string","description":"Order type"},"Network":{"enum":["mainnet","bnbSmartChainMainnet","eosMainnet","bnbSmartChainTestnet","polygonMainnet","fantomMainnet","eosTestnet","bitcoinMainnet","cosmosHubTestnet","cosmosHub","bitcoinTestnet","bchMainnet","bchTestnet","solanaMainnet","solanaDevnet","polkadotMainnet","polkadotWestend","cardanoMainnet","cardanoTestnet","algorandMainnet","algorandTestnet","stellarMainnet","stellarTestnet","litecoinMainnet","litecoinTestnet","tezosMainnet","tezosTestnet","arbitrumMainnet","avalancheFuji","avalancheMainnet","polygonAmoy","rippleMainnet","rippleTestnet","arbitrumSepolia","dogeTestnet","dogeMainnet","nearMainnet","nearTestnet","tronMainnet","tronTestnet","flowMainnet","flowTestnet","hederaMainnet","hederaTestnet","sepolia"],"type":"string","description":"Supported crypto networks"},"OrganisationRefundsDataRequestModel":{"type":"object","properties":{"status":{"$ref":"#/components/schemas/PartiallyFilledOrderStatus"},"fromDate":{"type":"string","description":"Date from","format":"date-time","nullable":true},"toDate":{"type":"string","description":"Date to","format":"date-time","nullable":true}},"additionalProperties":false},"OtcTradeRequestModel":{"required":["accountId","from","organizationId","price","to"],"type":"object","properties":{"accountId":{"minLength":1,"type":"string","description":"Custodial account identifier","format":"uuid"},"type":{"$ref":"#/components/schemas/ModelOrderType"},"from":{"$ref":"#/components/schemas/AssetDataFrom"},"to":{"$ref":"#/components/schemas/AssetData"},"comment":{"maxLength":1000,"type":"string","description":"Gets or sets the comment.","nullable":true},"spreadBasisPoints":{"type":"number","description":"Integrator spread basis points","format":"double","nullable":true},"spreadFiatPerUnit":{"type":"number","description":"Integrator spread fixed amount (for PM trading ONLY)","format":"double","nullable":true},"organizationId":{"minLength":1,"type":"string","description":"Organization account identifier","format":"uuid"},"fortressMarkup":{"minimum":0,"type":"number","description":"Gets or sets the fortress markup.","format":"double","nullable":true},"marketMakerOrLP":{"type":"string","description":"Gets or sets the market maker or liquidity provider.","nullable":true},"price":{"minimum":0,"exclusiveMinimum":true,"type":"number","description":"Gets or sets the price for 1 crypto.","format":"double"}},"additionalProperties":false,"description":"Buy/sell crypto request model"},"OtcTradeResponseModel":{"type":"object","properties":{"paymentId":{"type":"string","description":"Gets or sets the payment identifier","format":"uuid"},"organizationId":{"type":"string","description":"Gets or sets the organization identifier","format":"uuid"},"custodialAccountId":{"type":"string","description":"Gets or sets the custodial account identifier","format":"uuid"},"paymentType":{"$ref":"#/components/schemas/PaymentType"},"assetType":{"type":"string","description":"Gets or sets the asset type","nullable":true},"network":{"$ref":"#/components/schemas/ModelNetworkChain"},"amount":{"type":"number","description":"Gets or sets the amount","format":"double","nullable":true},"cryptoAmount":{"type":"number","description":"Gets or sets the amount","format":"double","nullable":true},"fortressMarkupAmount":{"type":"number","description":"Gets or sets the fortress markup amount","format":"double","nullable":true},"integratorsMarkupAmount":{"type":"number","description":"Gets or sets the integrators markup amount","format":"double","nullable":true},"price":{"type":"number","description":"Gets or sets the price","format":"double","nullable":true},"createdAt":{"type":"string","description":"Gets or sets the created at","format":"date-time"}},"additionalProperties":false,"description":"OTC trade response model"},"OtcTradeResponseModelPageResponseModel":{"type":"object","properties":{"data":{"type":"array","items":{"$ref":"#/components/schemas/OtcTradeResponseModel"},"description":"Gets or sets the data.","nullable":true},"meta":{"$ref":"#/components/schemas/PageMetadata"}},"additionalProperties":false},"OtcTradeStatus":{"enum":["completed","aborted"],"type":"string","description":"OTC trade status"},"PageMetadata":{"type":"object","properties":{"pageCount":{"type":"integer","format":"int32"},"resourceCount":{"type":"integer","format":"int32"}},"additionalProperties":false},"PartiallyFilledOrderStatus":{"enum":["new","inProgress","completed","failed"],"type":"string"},"PaymentStatus":{"enum":["new","completed","approvalNeeded","rejected"],"type":"string","description":"Payment status"},"PaymentType":{"enum":["internal","cardDeposit","cardWithdrawal","achDeposit","achWithdrawal","wireDeposit","wireWithdrawal","buyCrypto","sellCrypto","depositCrypto","withdrawalCrypto","internalCrypto","privateSecurityDeposit","privateSecurityWithdrawal","privateSecurityInternal","incomingAchDeposit","incomingAchWithdrawal","checkDeposit","buyPreciousMetal","sellPreciousMetal"],"type":"string","description":"Payment type"},"PreciousMetalPrice":{"type":"object","properties":{"buy":{"type":"number","format":"double"},"sell":{"type":"number","format":"double"}},"additionalProperties":false},"PreciousMetalPriceRequestFilter":{"type":"object","properties":{"spreadBasisPoints":{"type":"number","description":"Integrator spread basis points","format":"double","nullable":true},"spreadFiatPerUnit":{"type":"number","description":"Integrator spread fiat per unit","format":"double","nullable":true}},"additionalProperties":false},"PreciousMetalPriceResponseModel":{"type":"object","properties":{"price":{"$ref":"#/components/schemas/PreciousMetalPrice"}},"additionalProperties":false},"PreciousMetalType":{"enum":["gold","silver"],"type":"string"},"Price":{"type":"object","properties":{"buy":{"type":"number","description":"Buy price","format":"double"},"sell":{"type":"number","description":"Sell price","format":"double"}},"additionalProperties":false,"description":"Price model"},"ProblemDetails":{"type":"object","properties":{"type":{"type":"string","nullable":true},"title":{"type":"string","nullable":true},"status":{"type":"integer","format":"int32","nullable":true},"detail":{"type":"string","nullable":true},"instance":{"type":"string","nullable":true}},"additionalProperties":{}},"TalosOrderConfigurationItemResponse":{"type":"object","properties":{"timeInForce":{"$ref":"#/components/schemas/TimeInForce"},"organizationId":{"type":"string","format":"uuid"}},"additionalProperties":false},"TalosOrderConfigurationResponse":{"type":"object","properties":{"timeInForce":{"$ref":"#/components/schemas/TimeInForce"}},"additionalProperties":false},"TalosOrderConfigurationsResponse":{"type":"object","properties":{"talosOrderConfigurationItems":{"type":"array","items":{"$ref":"#/components/schemas/TalosOrderConfigurationItemResponse"},"nullable":true}},"additionalProperties":false},"TimeInForce":{"enum":["goodTillCancel","fillOrKill","fillAndKill","postOnly"],"type":"string"},"TradeRequestModel":{"required":["accountId","from","to"],"type":"object","properties":{"accountId":{"minLength":1,"type":"string","description":"Custodial account identifier","format":"uuid"},"type":{"$ref":"#/components/schemas/ModelOrderType"},"from":{"$ref":"#/components/schemas/AssetDataFrom"},"to":{"$ref":"#/components/schemas/AssetData"},"comment":{"maxLength":1000,"type":"string","description":"Gets or sets the comment.","nullable":true},"spreadBasisPoints":{"type":"number","description":"Integrator spread basis points","format":"double","nullable":true},"spreadFiatPerUnit":{"type":"number","description":"Integrator spread fixed amount (for PM trading ONLY)","format":"double","nullable":true}},"additionalProperties":false,"description":"Buy/sell crypto request model"},"TradeResponseModel":{"type":"object","properties":{"id":{"type":"string","description":"Payment identifier","format":"uuid"},"type":{"$ref":"#/components/schemas/PaymentType"},"status":{"$ref":"#/components/schemas/PaymentStatus"},"source":{"$ref":"#/components/schemas/FundsStorageResponseModel"},"destination":{"$ref":"#/components/schemas/FundsStorageResponseModel"},"comment":{"type":"string","description":"Comment","nullable":true},"funds":{"type":"number","description":"Funds","format":"double","nullable":true},"cryptoAmount":{"type":"number","description":"Crypto amount","format":"double","nullable":true},"quantity":{"type":"number","description":"Precious metal quantity","format":"double","nullable":true},"currency":{"$ref":"#/components/schemas/ModelAssetFiatType"},"sourceCurrency":{"$ref":"#/components/schemas/ModelAssetFiatType"},"destinationCurrency":{"$ref":"#/components/schemas/ModelAssetFiatType"},"assetTypeId":{"type":"string","description":"Id of Asset type (for Private Security)","format":"uuid","nullable":true},"network":{"$ref":"#/components/schemas/ModelNetworkChain"},"spreadBasisPoints":{"type":"number","description":"Integrator spread basis points","format":"double","nullable":true},"spreadFiatPerUnit":{"type":"number","description":"Integrator spread fiat per unit","format":"double","nullable":true},"txHash":{"type":"string","description":"Transaction hash","nullable":true}},"additionalProperties":false,"description":"Payment response model"},"TradingPairDataModel":{"type":"object","properties":{"symbol":{"type":"string","description":"The name of the trading pair to add (for example: \"BTC-USD\")","nullable":true},"customBids":{"type":"object","additionalProperties":{"type":"string"},"description":"Optional custom bids","nullable":true},"customAsks":{"type":"object","additionalProperties":{"type":"string"},"description":"Optional custom adds","nullable":true},"shouldUseValuesFromConfig":{"type":"boolean","description":"Whether to use values from configuration instead (in this case you wouldn't needs custom bids and asks)"}},"additionalProperties":false,"description":"Model for adding mocked trading pairs in fake storage"},"TradingPairModel":{"required":["tradingPair"],"type":"object","properties":{"tradingPair":{"minLength":1,"type":"string","description":"Trading pair"}},"additionalProperties":false,"description":"Trading pair name"},"UpdateOtcTradeRequestModel":{"type":"object","properties":{"status":{"$ref":"#/components/schemas/OtcTradeStatus"}},"additionalProperties":false,"description":"Update OTC trade request model"},"UpdateTalosOrderConfigurationRequest":{"type":"object","properties":{"organizationId":{"type":"string","format":"uuid"},"timeInForce":{"$ref":"#/components/schemas/TimeInForce"}},"additionalProperties":false}},"securitySchemes":{"Bearer":{"type":"apiKey","description":"Put access token in the box below.<br>For example: <b>Bearer eyJ0eXAiOiJKV1QiLCJhbGciOiJSUzI1NiIsImtpZCI6I</b>","name":"Authorization","in":"header"}}},"security":[{"Bearer":[]}],"x-readme":{"explorer-enabled":true,"proxy-enabled":true}}